diagonalpy-0.2.0.dist-info/METADATA
diagonalpy-0.2.0.dist-info/WHEEL
diagonalpy-0.2.0.dist-info/entry_points.txt
diagonalpy-0.2.0.dist-info/licenses/LICENSE
diagonalpy/__init__.py
diagonalpy/convert.py
diagonalpy/delete.py
diagonalpy/deploy.py
diagonalpy/models/linear_model.py
diagonalpy/save.py
diagonalpy/sklearn/linear_model.py
diagonalpy-0.2.0.dist-info/RECORD
