Metadata-Version: 2.1
Name: diagonalpy
Version: 0.2.0
Summary: deploy linear models from scikit-learn to diagonal.sh
Author: Leon Luithlen
Requires-Python: >=3.9
Requires-Dist: scikit-learn>=1.2.0
Requires-Dist: numpy>=1.24.0
Requires-Dist: onnx>=1.13.0
Requires-Dist: requests>=2.28.0
